{
  "id": "reminder.escalation.intensity-up",
  "title": "Ignored reminder escalates intensity on next check",
  "domain": "reminders",
  "tags": [
    "lifeops",
    "reminders",
    "escalation",
    "retry-after-failure"
  ],
  "status": "failed",
  "durationMs": 737,
  "providerName": "none",
  "startedAtIso": "2026-04-17T00:17:07.280Z",
  "completedAtIso": "2026-04-17T00:17:08.017Z",
  "turns": [
    {
      "turnIndex": 0,
      "turnName": "seed urgent task",
      "requestSummary": "POST /api/lifeops/definitions",
      "responseText": "",
      "plannerText": "",
      "actionsCalled": [],
      "durationMs": 0,
      "assertions": []
    },
    {
      "turnIndex": 1,
      "turnName": "process first reminder",
      "requestSummary": "POST /api/lifeops/reminders/process",
      "responseText": "",
      "plannerText": "",
      "actionsCalled": [],
      "durationMs": 0,
      "assertions": []
    },
    {
      "turnIndex": 2,
      "turnName": "process escalated reminder after ignore",
      "requestSummary": "POST /api/lifeops/reminders/process",
      "responseText": "",
      "plannerText": "",
      "actionsCalled": [],
      "durationMs": 0,
      "assertions": []
    }
  ],
  "finalChecks": [
    {
      "label": "reminderIntensity:Call dentist",
      "status": "failed",
      "detail": "Not yet implemented — LifeOps-style final checks require the runner to boot the /api/lifeops endpoints. Set runtime.__scenarioApiPort or wait on the T2-api-server integration."
    }
  ],
  "actionsCalled": [],
  "cleanup": [],
  "cost": {
    "provider": "none",
    "usd": 0,
    "tokensIn": 0,
    "tokensOut": 0
  },
  "llmCallCount": 0
}